setup.py
gg_module/__init__.py
gg_module/core.py
gg_module.egg-info/PKG-INFO
gg_module.egg-info/SOURCES.txt
gg_module.egg-info/dependency_links.txt
gg_module.egg-info/top_level.txt