Metadata-Version: 1.0
Name: gg-module
Version: 0.0.4
Summary: gg module
Home-page: UNKNOWN
Author: gg
Author-email: UNKNOWN
License: UNKNOWN
Platform: UNKNOWN
